[{"name":"naasir/emacs.d","owner":"naasir","html_url":"https://github.com/naasir/emacs.d","stars":0,"forks":0,"watchers":1,"issues":0,"language":"Emacs Lisp","description":"My emacs config","topics":[],"score":1917,"global_rank":352132},{"name":"mkheck/eureka-test-client","owner":"mkheck","html_url":"https://github.com/mkheck/eureka-test-client","stars":0,"forks":0,"watchers":1,"issues":0,"language":"Shell","description":"Basic client app for testing connection/address assignment by Eureka server.","topics":[],"score":1917,"global_rank":352143},{"name":"mkheck/config-service","owner":"mkheck","html_url":"https://github.com/mkheck/config-service","stars":0,"forks":0,"watchers":1,"issues":0,"language":"Shell","description":null,"topics":[],"score":1917,"global_rank":352144},{"name":"vritant24/Tip-Jar","owner":"vritant24","html_url":"https://github.com/vritant24/Tip-Jar","stars":0,"forks":0,"watchers":1,"issues":1,"language":"Swift","description":"iOS swift application for calculation tips","topics":[],"score":1917,"global_rank":352148},{"name":"trodemaster/goargs","owner":"trodemaster","html_url":"https://github.com/trodemaster/goargs","stars":0,"forks":0,"watchers":1,"issues":0,"language":"Go","description":"testing out some methods for arguments and cli tool basics","topics":[],"score":1917,"global_rank":352166},{"name":"KalebPapesh/myemacsprogrammingtemplates","owner":"KalebPapesh","html_url":"https://github.com/KalebPapesh/myemacsprogrammingtemplates","stars":0,"forks":0,"watchers":1,"issues":0,"language":"Shell","description":"templates to auto fill commonly used information into a newly created file based off of extension","topics":[],"score":1917,"global_rank":352173},{"name":"lukewolcott/WearableComputingCourseraProject","owner":"lukewolcott","html_url":"https://github.com/lukewolcott/WearableComputingCourseraProject","stars":0,"forks":0,"watchers":1,"issues":0,"language":"R","description":"course project for Coursera course \"Getting and Cleaning Data\"","topics":[],"score":1917,"global_rank":352175},{"name":"ilebrero/Algo3-TP2","owner":"ilebrero","html_url":"https://github.com/ilebrero/Algo3-TP2","stars":0,"forks":0,"watchers":1,"issues":0,"language":"TeX","description":"Trabajo Practico N\u00b02 de la materia Algoritmos y Estructuras de Datos 3","topics":[],"score":1917,"global_rank":352195},{"name":"ilebrero/Algo3-TP1","owner":"ilebrero","html_url":"https://github.com/ilebrero/Algo3-TP1","stars":0,"forks":0,"watchers":1,"issues":0,"language":"TeX","description":"Trabajo Practico N\u00b01 de la materia Algoritmos y Estructuras de Datos 3","topics":[],"score":1917,"global_rank":352196},{"name":"asdf25jae/10-19-21","owner":"asdf25jae","html_url":"https://github.com/asdf25jae/10-19-21","stars":0,"forks":0,"watchers":1,"issues":0,"language":"Swift","description":"Simple blackjack/21 iPhone app made with Swift 2. First iPhone app","topics":[],"score":1917,"global_rank":352197},{"name":"krishfuria/Tic-Tac-Toe","owner":"krishfuria","html_url":"https://github.com/krishfuria/Tic-Tac-Toe","stars":0,"forks":0,"watchers":1,"issues":0,"language":"Swift","description":"iOS9 Swift 2 - Learning","topics":[],"score":1917,"global_rank":352201},{"name":"krishfuria/ImageAnimation","owner":"krishfuria","html_url":"https://github.com/krishfuria/ImageAnimation","stars":0,"forks":0,"watchers":1,"issues":0,"language":"Swift","description":"iOs9 Swift 2 - Learning ","topics":[],"score":1917,"global_rank":352202},{"name":"krishfuria/Whats-The-Weather","owner":"krishfuria","html_url":"https://github.com/krishfuria/Whats-The-Weather","stars":0,"forks":0,"watchers":1,"issues":0,"language":"Swift","description":"iOs9 Swift 2 - Learning","topics":[],"score":1917,"global_rank":352203},{"name":"krishfuria/To-Do-List","owner":"krishfuria","html_url":"https://github.com/krishfuria/To-Do-List","stars":0,"forks":0,"watchers":1,"issues":0,"language":"Swift","description":"iOS9 Swift 2 - Learning","topics":[],"score":1917,"global_rank":352204},{"name":"krishfuria/TimesTable","owner":"krishfuria","html_url":"https://github.com/krishfuria/TimesTable","stars":0,"forks":0,"watchers":1,"issues":0,"language":"Swift","description":"iOS9 Swift 2","topics":[],"score":1917,"global_rank":352205},{"name":"krishfuria/Timer-App","owner":"krishfuria","html_url":"https://github.com/krishfuria/Timer-App","stars":0,"forks":0,"watchers":1,"issues":0,"language":"Swift","description":"iOS 9 Swift 2","topics":[],"score":1917,"global_rank":352206},{"name":"sruthirameshv/algorithm-design","owner":"sruthirameshv","html_url":"https://github.com/sruthirameshv/algorithm-design","stars":0,"forks":0,"watchers":1,"issues":0,"language":"Haskell","description":"selected exercises from the Algorithm Design Manual, 2nd Edition","topics":[],"score":1917,"global_rank":352217},{"name":"EmmanuelTsouris/SpriteKit-Physics-Collisions-in-Swift","owner":"EmmanuelTsouris","html_url":"https://github.com/EmmanuelTsouris/SpriteKit-Physics-Collisions-in-Swift","stars":0,"forks":0,"watchers":1,"issues":0,"language":"Swift","description":"A Swift version of Apple's objective-c sample: SpriteKit Physics Collisions","topics":[],"score":1917,"global_rank":352221},{"name":"SatyamJ/MobileApps","owner":"SatyamJ","html_url":"https://github.com/SatyamJ/MobileApps","stars":0,"forks":0,"watchers":1,"issues":1,"language":"Swift","description":null,"topics":[],"score":1917,"global_rank":352228},{"name":"quinkennedy/social-buzz","owner":"quinkennedy","html_url":"https://github.com/quinkennedy/social-buzz","stars":0,"forks":0,"watchers":1,"issues":0,"language":"Clojure","description":"a web app for finding and liking posts (initially instagram)","topics":[],"score":1917,"global_rank":352230},{"name":"penguin1214/MyDatabase","owner":"penguin1214","html_url":"https://github.com/penguin1214/MyDatabase","stars":0,"forks":0,"watchers":1,"issues":0,"language":"Objective-C","description":null,"topics":[],"score":1917,"global_rank":352238},{"name":"kaylarose/Cupertino_Theme","owner":"kaylarose","html_url":"https://github.com/kaylarose/Cupertino_Theme","stars":5,"forks":0,"watchers":1,"issues":0,"language":"Other","description":"jQuery theme inspired by Apple","topics":[],"score":1916.8000000000002,"global_rank":352242},{"name":"VoiceCode/community","owner":"VoiceCode","html_url":"https://github.com/VoiceCode/community","stars":2,"forks":0,"watchers":2,"issues":0,"language":"Other","description":"A place where people can link to their custom code, settings, commands, packages, related projects, or helpful resources","topics":[],"score":1916.8000000000002,"global_rank":352243},{"name":"ScottDuckworth/openssh-stdinkey","owner":"ScottDuckworth","html_url":"https://github.com/ScottDuckworth/openssh-stdinkey","stars":2,"forks":1,"watchers":1,"issues":0,"language":"Other","description":"A fork of OpenSSH which sends the user's public key to stdin of AuthorizedKeysCommand","topics":[],"score":1916.8000000000002,"global_rank":352244},{"name":"GwG422/ClashTLS","owner":"GwG422","html_url":"https://github.com/GwG422/ClashTLS","stars":1,"forks":0,"watchers":0,"issues":0,"language":"Other","description":"A heavily redacted uncompilable certificate pinning bypass module for clash of streamers","topics":[],"score":1916.8000000000002,"global_rank":352245},{"name":"GwG422/rubberducky","owner":"GwG422","html_url":"https://github.com/GwG422/rubberducky","stars":1,"forks":0,"watchers":0,"issues":0,"language":"Other","description":null,"topics":[],"score":1916.8000000000002,"global_rank":352246},{"name":"hello-yyx/Terminal-setting","owner":"hello-yyx","html_url":"https://github.com/hello-yyx/Terminal-setting","stars":1,"forks":0,"watchers":1,"issues":0,"language":"Other","description":null,"topics":[],"score":1916.8000000000002,"global_rank":352247},{"name":"djl218/hello-world","owner":"djl218","html_url":"https://github.com/djl218/hello-world","stars":1,"forks":0,"watchers":0,"issues":0,"language":"Other","description":"My very first repository!","topics":[],"score":1916.8000000000002,"global_rank":352248},{"name":"Rajat-dhyani/100DaysOfML","owner":"Rajat-dhyani","html_url":"https://github.com/Rajat-dhyani/100DaysOfML","stars":1,"forks":0,"watchers":1,"issues":0,"language":"Other","description":"I am taking up the challenge to practice  Machine Learning at least an hour everyday for next 100 days!!","topics":[],"score":1916.8000000000002,"global_rank":352249},{"name":"UWFosterIT/.github","owner":"UWFosterIT","html_url":"https://github.com/UWFosterIT/.github","stars":0,"forks":0,"watchers":4,"issues":0,"language":"Other","description":null,"topics":[],"score":1916.8000000000002,"global_rank":352250},{"name":"patkaehuaea/ansible-bootstrap","owner":"patkaehuaea","html_url":"https://github.com/patkaehuaea/ansible-bootstrap","stars":0,"forks":0,"watchers":1,"issues":0,"language":"Other","description":"Manage configuration with Ansible.","topics":[],"score":1916.8000000000002,"global_rank":352251},{"name":"wellsiau-aws/test-cfn-lint-action","owner":"wellsiau-aws","html_url":"https://github.com/wellsiau-aws/test-cfn-lint-action","stars":0,"forks":1,"watchers":1,"issues":1,"language":"Other","description":null,"topics":[],"score":1916.8000000000002,"global_rank":352252},{"name":"elleem/elleem","owner":"elleem","html_url":"https://github.com/elleem/elleem","stars":0,"forks":0,"watchers":1,"issues":0,"language":"Other","description":"About me","topics":[],"score":1916.8000000000002,"global_rank":352253},{"name":"jsalexan/jsalexan","owner":"jsalexan","html_url":"https://github.com/jsalexan/jsalexan","stars":0,"forks":0,"watchers":1,"issues":0,"language":"Other","description":"This is my GitHub profile. I created it with the assistance of GPRM's profile generator. You can find the link to the page at the bottom of my profile. ","topics":["config","github-config"],"score":1916.8000000000002,"global_rank":352254},{"name":"issaquahd/Terraform_ERA","owner":"issaquahd","html_url":"https://github.com/issaquahd/Terraform_ERA","stars":0,"forks":1,"watchers":1,"issues":0,"language":"Other","description":"using terraform for DBaaS","topics":[],"score":1916.8000000000002,"global_rank":352255},{"name":"keppy/keppy","owner":"keppy","html_url":"https://github.com/keppy/keppy","stars":0,"forks":0,"watchers":1,"issues":0,"language":"Other","description":null,"topics":[],"score":1916.8000000000002,"global_rank":352256},{"name":"lana-20/mobile-app-types","owner":"lana-20","html_url":"https://github.com/lana-20/mobile-app-types","stars":0,"forks":0,"watchers":1,"issues":0,"language":"Other","description":null,"topics":[],"score":1916.8000000000002,"global_rank":352257},{"name":"upbound/caas-test","owner":"upbound","html_url":"https://github.com/upbound/caas-test","stars":0,"forks":0,"watchers":2,"issues":0,"language":"Other","description":null,"topics":[],"score":1916.8000000000002,"global_rank":352258},{"name":"gkroiz/gkroiz","owner":"gkroiz","html_url":"https://github.com/gkroiz/gkroiz","stars":0,"forks":0,"watchers":1,"issues":0,"language":"Other","description":null,"topics":[],"score":1916.8000000000002,"global_rank":352259},{"name":"jrolstad/aad-license-governor-deploy","owner":"jrolstad","html_url":"https://github.com/jrolstad/aad-license-governor-deploy","stars":0,"forks":1,"watchers":1,"issues":0,"language":"Other","description":null,"topics":[],"score":1916.8000000000002,"global_rank":352260},{"name":"DanielKobina/Japanese-to-English_Translations","owner":"DanielKobina","html_url":"https://github.com/DanielKobina/Japanese-to-English_Translations","stars":0,"forks":0,"watchers":1,"issues":0,"language":"Other","description":null,"topics":[],"score":1916.8000000000002,"global_rank":352261},{"name":"J-DUB64/js-capstone","owner":"J-DUB64","html_url":"https://github.com/J-DUB64/js-capstone","stars":0,"forks":1,"watchers":0,"issues":0,"language":"Other","description":null,"topics":[],"score":1916.8000000000002,"global_rank":352262},{"name":"dansi21/EDSM.NET","owner":"dansi21","html_url":"https://github.com/dansi21/EDSM.NET","stars":0,"forks":0,"watchers":1,"issues":0,"language":"Other","description":null,"topics":[],"score":1916.8000000000002,"global_rank":352263},{"name":"romanprotoliuk/ai-doctor","owner":"romanprotoliuk","html_url":"https://github.com/romanprotoliuk/ai-doctor","stars":0,"forks":0,"watchers":1,"issues":0,"language":"Other","description":"Brainstorm session ai doctor ","topics":[],"score":1916.8000000000002,"global_rank":352264},{"name":"socrata/tSocrata","owner":"socrata","html_url":"https://github.com/socrata/tSocrata","stars":0,"forks":0,"watchers":20,"issues":0,"language":"Other","description":"Socrata Talend connector","topics":["data-integration"],"score":1916.8000000000002,"global_rank":352265},{"name":"eannefawcett/eannefawcett","owner":"eannefawcett","html_url":"https://github.com/eannefawcett/eannefawcett","stars":0,"forks":0,"watchers":1,"issues":0,"language":"Other","description":null,"topics":[],"score":1916.8000000000002,"global_rank":352266},{"name":"andrerod/swerc","owner":"andrerod","html_url":"https://github.com/andrerod/swerc","stars":3,"forks":0,"watchers":1,"issues":0,"language":"Other","description":"Presentation for Swerc 2015","topics":[],"score":1916.0,"global_rank":352267},{"name":"DHager/mvn-repo","owner":"DHager","html_url":"https://github.com/DHager/mvn-repo","stars":2,"forks":2,"watchers":1,"issues":0,"language":"Other","description":"A pseudo-project for hosting maven artifacts from other projects","topics":[],"score":1916.0,"global_rank":352268},{"name":"mrbrutti/rbee","owner":"mrbrutti","html_url":"https://github.com/mrbrutti/rbee","stars":2,"forks":0,"watchers":1,"issues":0,"language":"Other","description":"...","topics":[],"score":1916.0,"global_rank":352269},{"name":"coolgod/coolgod.github.io-vuepress","owner":"coolgod","html_url":"https://github.com/coolgod/coolgod.github.io-vuepress","stars":1,"forks":0,"watchers":1,"issues":22,"language":"Other","description":null,"topics":[],"score":1916.0,"global_rank":352272}]