[{"name":"jesterb0206/Rosa","owner":"jesterb0206","html_url":"https://github.com/jesterb0206/Rosa","stars":2,"forks":1,"watchers":1,"issues":0,"language":"HTML","description":null,"topics":[],"score":2861,"global_rank":27632},{"name":"amcrisan/GEViTAnalysisRelease","owner":"amcrisan","html_url":"https://github.com/amcrisan/GEViTAnalysisRelease","stars":3,"forks":2,"watchers":1,"issues":0,"language":"HTML","description":"A systematic method for surveying data visualizations and a resulting genomic epidemiology visualization typology: GEViT","topics":["bioinformatics","data-visualization","methods-paper"],"score":2860,"global_rank":27677},{"name":"jesterb0206/FAQ-Collapse","owner":"jesterb0206","html_url":"https://github.com/jesterb0206/FAQ-Collapse","stars":2,"forks":1,"watchers":1,"issues":0,"language":"HTML","description":"Project 12 of 50 Projects In 50 Days - HTML, CSS, and JavaScript","topics":[],"score":2860,"global_rank":27688},{"name":"jesterb0206/Sound-Board","owner":"jesterb0206","html_url":"https://github.com/jesterb0206/Sound-Board","stars":2,"forks":1,"watchers":1,"issues":0,"language":"HTML","description":"Project 9 of 50 Projects In 50 Days - HTML, CSS, and JavaScript","topics":[],"score":2860,"global_rank":27691},{"name":"jesterb0206/Scroll-Animation","owner":"jesterb0206","html_url":"https://github.com/jesterb0206/Scroll-Animation","stars":2,"forks":1,"watchers":1,"issues":0,"language":"HTML","description":"Project 6 of 50 Projects In 50 Days - HTML, CSS, and JavaScript","topics":[],"score":2860,"global_rank":27694},{"name":"Kitt-AI/docs","owner":"Kitt-AI","html_url":"https://github.com/Kitt-AI/docs","stars":2,"forks":6,"watchers":5,"issues":0,"language":"HTML","description":"Sphinx generated static HTML files","topics":[],"score":2860,"global_rank":27697},{"name":"nfongster/nfongster.github.io","owner":"nfongster","html_url":"https://github.com/nfongster/nfongster.github.io","stars":0,"forks":0,"watchers":1,"issues":0,"language":"HTML","description":"Source code for my personal website.","topics":[],"score":2860,"global_rank":27718},{"name":"karaatfullstack/day-1-project","owner":"karaatfullstack","html_url":"https://github.com/karaatfullstack/day-1-project","stars":0,"forks":12,"watchers":1,"issues":0,"language":"HTML","description":null,"topics":[],"score":2860,"global_rank":27719},{"name":"garybgenett/www.garybgenett.net","owner":"garybgenett","html_url":"https://github.com/garybgenett/www.garybgenett.net","stars":0,"forks":0,"watchers":1,"issues":0,"language":"HTML","description":null,"topics":[],"score":2860,"global_rank":27721},{"name":"schollz/prevent-link-rot","owner":"schollz","html_url":"https://github.com/schollz/prevent-link-rot","stars":17,"forks":2,"watchers":1,"issues":3,"language":"HTML","description":"Simple utility to convert links in any file to permanent links via the https://archive.org/web/ or http://perma.cc","topics":[],"score":2859,"global_rank":27729},{"name":"kaedenbrinkman/rivian-configurator","owner":"kaedenbrinkman","html_url":"https://github.com/kaedenbrinkman/rivian-configurator","stars":4,"forks":0,"watchers":1,"issues":0,"language":"HTML","description":"Poor man's configurator for Rivian R1S and R1T","topics":["r1s","r1t","rivian","rivian-configurator"],"score":2859,"global_rank":27754},{"name":"jesterb0206/Incrementing-Counter","owner":"jesterb0206","html_url":"https://github.com/jesterb0206/Incrementing-Counter","stars":2,"forks":1,"watchers":1,"issues":0,"language":"HTML","description":"Project 15 of 50 Projects In 50 Days - HTML, CSS, and JavaScript","topics":[],"score":2859,"global_rank":27769},{"name":"deltaryz/deltaryz.com","owner":"deltaryz","html_url":"https://github.com/deltaryz/deltaryz.com","stars":0,"forks":0,"watchers":1,"issues":0,"language":"HTML","description":"Personal portfolio website","topics":[],"score":2859,"global_rank":27784},{"name":"cjsmocjsmo/cjsmocjsmo.github.io","owner":"cjsmocjsmo","html_url":"https://github.com/cjsmocjsmo/cjsmocjsmo.github.io","stars":0,"forks":0,"watchers":1,"issues":5,"language":"HTML","description":null,"topics":[],"score":2859,"global_rank":27788},{"name":"amyjko/informatics-teaching-guide","owner":"amyjko","html_url":"https://github.com/amyjko/informatics-teaching-guide","stars":11,"forks":2,"watchers":0,"issues":18,"language":"HTML","description":"A short book on teaching in the University of Washington Informatics undergraduate program.","topics":[],"score":2858,"global_rank":27794},{"name":"nickmmark/hemodynamic-calculations","owner":"nickmmark","html_url":"https://github.com/nickmmark/hemodynamic-calculations","stars":1,"forks":0,"watchers":1,"issues":0,"language":"HTML","description":"web calculator for hemodynamic parameters useful in patients with cardiogenic shock","topics":[],"score":2858,"global_rank":27836},{"name":"beetlebox-dev/top_domain","owner":"beetlebox-dev","html_url":"https://github.com/beetlebox-dev/top_domain","stars":0,"forks":0,"watchers":1,"issues":0,"language":"HTML","description":null,"topics":[],"score":2858,"global_rank":27838},{"name":"allenai/allennlp-gallery","owner":"allenai","html_url":"https://github.com/allenai/allennlp-gallery","stars":5,"forks":0,"watchers":1,"issues":5,"language":"HTML","description":"A gallery of projects built with AllenNLP","topics":["allennlp","nlp","pytorch"],"score":2857,"global_rank":27875},{"name":"mollybeach/pumpkin","owner":"mollybeach","html_url":"https://github.com/mollybeach/pumpkin","stars":3,"forks":0,"watchers":2,"issues":3,"language":"HTML","description":"\ud83c\udf83 Pumpkin: Python Application Heroku Buildpack Heroku Postgress CLI Scripts \ud83c\udf83","topics":["heroku-buildpack","heroku-cli-plugin","heroku-postgres","python3"],"score":2857,"global_rank":27880},{"name":"htohfa/htohfa.github.io","owner":"htohfa","html_url":"https://github.com/htohfa/htohfa.github.io","stars":0,"forks":0,"watchers":1,"issues":0,"language":"HTML","description":null,"topics":[],"score":2857,"global_rank":27900},{"name":"bootstrap4cc/finances","owner":"bootstrap4cc","html_url":"https://github.com/bootstrap4cc/finances","stars":2,"forks":4,"watchers":0,"issues":0,"language":"HTML","description":"Financial consulting website template","topics":[],"score":2856,"global_rank":27953},{"name":"Sage-Bionetworks/IDG-DREAM-Challenge-Analysis","owner":"Sage-Bionetworks","html_url":"https://github.com/Sage-Bionetworks/IDG-DREAM-Challenge-Analysis","stars":2,"forks":1,"watchers":7,"issues":0,"language":"HTML","description":"Analysis scripts for the IDG-DREAM Drug Kinase Binding Prediction Challenge ","topics":[],"score":2856,"global_rank":27960},{"name":"yutarour/cellsalive","owner":"yutarour","html_url":"https://github.com/yutarour/cellsalive","stars":1,"forks":2,"watchers":1,"issues":0,"language":"HTML","description":"This is for educational and is not intended in any shape or form to make profit. This site exists just to keep the legacy of cellsAlive published 1994 alive and well and to avoid the hassle of downloading, unzipping a file","topics":["biology","biology-education","education","highschool","oldschool","school-education","teachers","website"],"score":2856,"global_rank":27962},{"name":"Louismousine/lexia","owner":"Louismousine","html_url":"https://github.com/Louismousine/lexia","stars":6,"forks":0,"watchers":0,"issues":1,"language":"HTML","description":"lexia is a Chrome extension to aid dyslexic users browse the web","topics":[],"score":2855,"global_rank":27995},{"name":"ArtimusMaximus/resume","owner":"ArtimusMaximus","html_url":"https://github.com/ArtimusMaximus/resume","stars":0,"forks":0,"watchers":1,"issues":0,"language":"HTML","description":null,"topics":[],"score":2855,"global_rank":28035},{"name":"Chris-Bortel/Vacay","owner":"Chris-Bortel","html_url":"https://github.com/Chris-Bortel/Vacay","stars":2,"forks":1,"watchers":3,"issues":0,"language":"HTML","description":null,"topics":[],"score":2854,"global_rank":28066},{"name":"adamkucz/psych548","owner":"adamkucz","html_url":"https://github.com/adamkucz/psych548","stars":2,"forks":0,"watchers":2,"issues":0,"language":"HTML","description":null,"topics":[],"score":2854,"global_rank":28070},{"name":"niketan16/DV-Vast-Challenge-2021-MC2","owner":"niketan16","html_url":"https://github.com/niketan16/DV-Vast-Challenge-2021-MC2","stars":1,"forks":2,"watchers":1,"issues":0,"language":"HTML","description":null,"topics":[],"score":2854,"global_rank":28075},{"name":"spiralgenetics/boost","owner":"spiralgenetics","html_url":"https://github.com/spiralgenetics/boost","stars":1,"forks":2,"watchers":5,"issues":0,"language":"HTML","description":"Fork of the Boost C++ library with bazel support","topics":[],"score":2854,"global_rank":28077},{"name":"SkyKick/helm-charts","owner":"SkyKick","html_url":"https://github.com/SkyKick/helm-charts","stars":1,"forks":1,"watchers":7,"issues":0,"language":"HTML","description":"The SkyKick Helm charts.","topics":[],"score":2854,"global_rank":28083},{"name":"DivyanshuSheth/spreadsheet-qa","owner":"DivyanshuSheth","html_url":"https://github.com/DivyanshuSheth/spreadsheet-qa","stars":4,"forks":0,"watchers":1,"issues":0,"language":"HTML","description":"Question Answering over Spreadsheets","topics":[],"score":2853,"global_rank":28124},{"name":"codefellows/seattle-code-201n31","owner":"codefellows","html_url":"https://github.com/codefellows/seattle-code-201n31","stars":2,"forks":0,"watchers":5,"issues":0,"language":"HTML","description":"Course Repository","topics":[],"score":2853,"global_rank":28141},{"name":"newmanix/portal-it115","owner":"newmanix","html_url":"https://github.com/newmanix/portal-it115","stars":0,"forks":38,"watchers":1,"issues":5,"language":"HTML","description":null,"topics":[],"score":2853,"global_rank":28158},{"name":"yuandrew/yuandrew.github.io","owner":"yuandrew","html_url":"https://github.com/yuandrew/yuandrew.github.io","stars":0,"forks":0,"watchers":0,"issues":0,"language":"HTML","description":"Andrew Yuan's Personal Website","topics":[],"score":2853,"global_rank":28159},{"name":"h-griffin/griffinspetcare","owner":"h-griffin","html_url":"https://github.com/h-griffin/griffinspetcare","stars":0,"forks":0,"watchers":1,"issues":0,"language":"HTML","description":"buisness info website","topics":["css","firebase","html","js"],"score":2853,"global_rank":28165},{"name":"keagud/Resume","owner":"keagud","html_url":"https://github.com/keagud/Resume","stars":1,"forks":1,"watchers":1,"issues":0,"language":"HTML","description":"My resume","topics":[],"score":2852,"global_rank":28210},{"name":"ylegall/ylegall.github.io","owner":"ylegall","html_url":"https://github.com/ylegall/ylegall.github.io","stars":5,"forks":0,"watchers":2,"issues":0,"language":"HTML","description":"github static site","topics":[],"score":2851,"global_rank":28239},{"name":"immannino/vue-template","owner":"immannino","html_url":"https://github.com/immannino/vue-template","stars":2,"forks":0,"watchers":1,"issues":0,"language":"HTML","description":null,"topics":[],"score":2851,"global_rank":28255},{"name":"jeffpar/pc","owner":"jeffpar","html_url":"https://github.com/jeffpar/pc","stars":1,"forks":2,"watchers":1,"issues":0,"language":"HTML","description":"Landing page for pc.js.org","topics":[],"score":2851,"global_rank":28261},{"name":"mathlord2/mathlord2.github.io","owner":"mathlord2","html_url":"https://github.com/mathlord2/mathlord2.github.io","stars":1,"forks":0,"watchers":0,"issues":0,"language":"HTML","description":"Personal website at: https://mathlord2.github.io/","topics":[],"score":2851,"global_rank":28265},{"name":"kadealicious/kadesamson.com","owner":"kadealicious","html_url":"https://github.com/kadealicious/kadesamson.com","stars":0,"forks":0,"watchers":1,"issues":0,"language":"HTML","description":"Personal portfolio website.","topics":[],"score":2851,"global_rank":28269},{"name":"BoyanLiuu/react-tetris","owner":"BoyanLiuu","html_url":"https://github.com/BoyanLiuu/react-tetris","stars":0,"forks":0,"watchers":1,"issues":7,"language":"HTML","description":"An  react tetris","topics":[],"score":2851,"global_rank":28271},{"name":"dglgit/webCompute_sf","owner":"dglgit","html_url":"https://github.com/dglgit/webCompute_sf","stars":0,"forks":0,"watchers":1,"issues":0,"language":"HTML","description":null,"topics":[],"score":2851,"global_rank":28273},{"name":"Sage-Bionetworks/mpower-feature-analysis","owner":"Sage-Bionetworks","html_url":"https://github.com/Sage-Bionetworks/mpower-feature-analysis","stars":0,"forks":2,"watchers":5,"issues":1,"language":"HTML","description":null,"topics":[],"score":2851,"global_rank":28280},{"name":"openzoom/openzoom.org","owner":"openzoom","html_url":"https://github.com/openzoom/openzoom.org","stars":8,"forks":5,"watchers":0,"issues":0,"language":"HTML","description":"OpenZoom Website","topics":[],"score":2850,"global_rank":28291},{"name":"zaturnvalley/autonoir","owner":"zaturnvalley","html_url":"https://github.com/zaturnvalley/autonoir","stars":3,"forks":0,"watchers":1,"issues":0,"language":"HTML","description":"Site for my \ud68c\uc0acAUTO / Tech Noir Music Projects","topics":[],"score":2850,"global_rank":28303},{"name":"jacob-ebey/hyperscript-snippets","owner":"jacob-ebey","html_url":"https://github.com/jacob-ebey/hyperscript-snippets","stars":3,"forks":0,"watchers":1,"issues":0,"language":"HTML","description":"A collection of _hyperscript snippets","topics":[],"score":2850,"global_rank":28306},{"name":"Sage-Bionetworks/Tumor-Deconvolution-Challenge","owner":"Sage-Bionetworks","html_url":"https://github.com/Sage-Bionetworks/Tumor-Deconvolution-Challenge","stars":1,"forks":1,"watchers":3,"issues":0,"language":"HTML","description":null,"topics":[],"score":2850,"global_rank":28321},{"name":"PriceLab/fimoService","owner":"PriceLab","html_url":"https://github.com/PriceLab/fimoService","stars":7,"forks":1,"watchers":2,"issues":0,"language":"HTML","description":"The meme suite's fimo (find motif) as a microservice, written in python, with R and python clients","topics":[],"score":2849,"global_rank":28348},{"name":"Exochos/myPersonalPage","owner":"Exochos","html_url":"https://github.com/Exochos/myPersonalPage","stars":0,"forks":0,"watchers":1,"issues":0,"language":"HTML","description":"Personal React Page for Jeremy!","topics":[],"score":2849,"global_rank":28399}]