[{"name":"CurtisMorice/Reactjs_Stars","owner":"CurtisMorice","html_url":"https://github.com/CurtisMorice/Reactjs_Stars","stars":0,"forks":0,"issues":0,"language":"JavaScript","description":"learning mapping and creating list in Reactjs","topics":[],"score":2083,"global_rank":316460},{"name":"CurtisMorice/Student_List_Reactjs_MongoDB","owner":"CurtisMorice","html_url":"https://github.com/CurtisMorice/Student_List_Reactjs_MongoDB","stars":0,"forks":0,"issues":0,"language":"JavaScript","description":"student list using CRUD with MongoDB","topics":[],"score":2083,"global_rank":316461},{"name":"CurtisMorice/Reactjs_StarWars_API","owner":"CurtisMorice","html_url":"https://github.com/CurtisMorice/Reactjs_StarWars_API","stars":0,"forks":0,"issues":0,"language":"JavaScript","description":"use of the SWAPI aka starwars api and populating list in react. ","topics":[],"score":2083,"global_rank":316462},{"name":"CurtisMorice/Gallery_Reactjs","owner":"CurtisMorice","html_url":"https://github.com/CurtisMorice/Gallery_Reactjs","stars":0,"forks":0,"issues":0,"language":"JavaScript","description":"card gallery for life story","topics":[],"score":2083,"global_rank":316463},{"name":"CurtisMorice/employee_salary_conversion_Reactjs","owner":"CurtisMorice","html_url":"https://github.com/CurtisMorice/employee_salary_conversion_Reactjs","stars":0,"forks":0,"issues":0,"language":"JavaScript","description":null,"topics":[],"score":2083,"global_rank":316464},{"name":"CurtisMorice/redux-axios","owner":"CurtisMorice","html_url":"https://github.com/CurtisMorice/redux-axios","stars":0,"forks":0,"issues":0,"language":"JavaScript","description":"Learning tool for redux and axios ","topics":[],"score":2083,"global_rank":316465},{"name":"Tellefsonjr/photo_gallery","owner":"Tellefsonjr","html_url":"https://github.com/Tellefsonjr/photo_gallery","stars":0,"forks":0,"issues":0,"language":"JavaScript","description":"Photo Gallery Site","topics":[],"score":2083,"global_rank":316466},{"name":"cnelson87/ReddAppRNExpo","owner":"cnelson87","html_url":"https://github.com/cnelson87/ReddAppRNExpo","stars":0,"forks":0,"issues":17,"language":"JavaScript","description":null,"topics":[],"score":2083,"global_rank":316469},{"name":"brianyamasaki/duke-game","owner":"brianyamasaki","html_url":"https://github.com/brianyamasaki/duke-game","stars":0,"forks":0,"issues":0,"language":"JavaScript","description":null,"topics":[],"score":2083,"global_rank":316471},{"name":"mashuaihh/TypingExercise","owner":"mashuaihh","html_url":"https://github.com/mashuaihh/TypingExercise","stars":0,"forks":0,"issues":16,"language":"JavaScript","description":"Personal typing exercise web app","topics":[],"score":2083,"global_rank":316472},{"name":"ben-davenport/Airbnb-Clone-Front-End","owner":"ben-davenport","html_url":"https://github.com/ben-davenport/Airbnb-Clone-Front-End","stars":0,"forks":0,"issues":5,"language":"JavaScript","description":"Airbnb Clone made with React, Redux, Materialize","topics":[],"score":2083,"global_rank":316473},{"name":"WillHK/totallyrealnews","owner":"WillHK","html_url":"https://github.com/WillHK/totallyrealnews","stars":0,"forks":0,"issues":0,"language":"JavaScript","description":"Totally real news for a totally real world","topics":[],"score":2083,"global_rank":316475},{"name":"keego/sandbox","owner":"keego","html_url":"https://github.com/keego/sandbox","stars":0,"forks":0,"issues":0,"language":"JavaScript","description":"A monorepo for my little experiments","topics":[],"score":2083,"global_rank":316476},{"name":"martinrrm/datocms-next-js-blog-demo-4756","owner":"martinrrm","html_url":"https://github.com/martinrrm/datocms-next-js-blog-demo-4756","stars":0,"forks":0,"issues":13,"language":"JavaScript","description":null,"topics":[],"score":2083,"global_rank":316477},{"name":"codeslikejaggars/knex-boilerplate","owner":"codeslikejaggars","html_url":"https://github.com/codeslikejaggars/knex-boilerplate","stars":0,"forks":0,"issues":0,"language":"JavaScript","description":"Knex and Bookshelf boilerplate","topics":["bookshelf","knex","nodejs","sqlite"],"score":2083,"global_rank":316478},{"name":"JakeNocentino/color-game","owner":"JakeNocentino","html_url":"https://github.com/JakeNocentino/color-game","stars":0,"forks":0,"issues":1,"language":"JavaScript","description":"An interactive web application color guessing game. In this game, you are presented with 6 different colors (or 3, if you choose easy mode) on the screen. You are also given an rgb color value that one of the colored squares on the screen hold. If you match the correct square with the displayed rgb color value, you win!","topics":[],"score":2083,"global_rank":316512},{"name":"viv-r/kaggle-trackml-event-viewer","owner":"viv-r","html_url":"https://github.com/viv-r/kaggle-trackml-event-viewer","stars":0,"forks":0,"issues":0,"language":"JavaScript","description":"A WebGL app to visualize the Kaggle TrackML competition dataset.","topics":[],"score":2083,"global_rank":316513},{"name":"viv-r/topic-modeling-reddit","owner":"viv-r","html_url":"https://github.com/viv-r/topic-modeling-reddit","stars":0,"forks":0,"issues":0,"language":"JavaScript","description":"Data 515 Project - LDA topic modeling on the Reddit jokes dataset","topics":[],"score":2083,"global_rank":316514},{"name":"nak1411/nak-hike","owner":"nak1411","html_url":"https://github.com/nak1411/nak-hike","stars":0,"forks":0,"issues":0,"language":"JavaScript","description":"Hike logging app","topics":[],"score":2083,"global_rank":316527},{"name":"nputhiyadath/nodejsAuthentication","owner":"nputhiyadath","html_url":"https://github.com/nputhiyadath/nodejsAuthentication","stars":0,"forks":0,"issues":0,"language":"JavaScript","description":null,"topics":[],"score":2083,"global_rank":316529},{"name":"jaydeepingle/react-es6-components","owner":"jaydeepingle","html_url":"https://github.com/jaydeepingle/react-es6-components","stars":0,"forks":0,"issues":0,"language":"JavaScript","description":"Demonstrate react class and es6 components","topics":[],"score":2083,"global_rank":316533},{"name":"njbraun/rollup-typescript","owner":"njbraun","html_url":"https://github.com/njbraun/rollup-typescript","stars":0,"forks":0,"issues":0,"language":"JavaScript","description":"Boilerplate example of using Typescript to a create small (single file) node app that can be run as a microservice.","topics":[],"score":2083,"global_rank":316538},{"name":"stephaniesmith/salmon-cookies-TA","owner":"stephaniesmith","html_url":"https://github.com/stephaniesmith/salmon-cookies-TA","stars":0,"forks":0,"issues":0,"language":"JavaScript","description":"Salmon Cookies Lab - Working on code to help students","topics":[],"score":2083,"global_rank":316539},{"name":"millanp/angulartutorial","owner":"millanp","html_url":"https://github.com/millanp/angulartutorial","stars":0,"forks":0,"issues":0,"language":"TypeScript","description":null,"topics":[],"score":2083,"global_rank":316540},{"name":"webdevdaemon/cmdev-gatsby","owner":"webdevdaemon","html_url":"https://github.com/webdevdaemon/cmdev-gatsby","stars":0,"forks":0,"issues":0,"language":"JavaScript","description":null,"topics":[],"score":2083,"global_rank":316542},{"name":"phil-mac/homeschool-guide-prototype","owner":"phil-mac","html_url":"https://github.com/phil-mac/homeschool-guide-prototype","stars":0,"forks":0,"issues":23,"language":"JavaScript","description":"tool to design and develop curriculum for a homeschool guide app","topics":[],"score":2083,"global_rank":316546},{"name":"rclarkmorrow/coffee_shop_menu","owner":"rclarkmorrow","html_url":"https://github.com/rclarkmorrow/coffee_shop_menu","stars":0,"forks":0,"issues":26,"language":"TypeScript","description":"Authorization tokens w/ Auth0 (Project for Udacity's Full Stack Nanodegree program)","topics":[],"score":2083,"global_rank":316549},{"name":"lynnkuh/DevConnector","owner":"lynnkuh","html_url":"https://github.com/lynnkuh/DevConnector","stars":0,"forks":0,"issues":0,"language":"JavaScript","description":"Social media react project","topics":[],"score":2083,"global_rank":316553},{"name":"sagecodes/memory-game","owner":"sagecodes","html_url":"https://github.com/sagecodes/memory-game","stars":0,"forks":0,"issues":0,"language":"JavaScript","description":"A memory card matching game built in Javascript","topics":[],"score":2083,"global_rank":316554},{"name":"LeoXia360/nihowdy","owner":"LeoXia360","html_url":"https://github.com/LeoXia360/nihowdy","stars":0,"forks":0,"issues":20,"language":"JavaScript","description":"Personal website","topics":[],"score":2083,"global_rank":316555},{"name":"wereallmonks/classsed-react-firebase-functions","owner":"wereallmonks","html_url":"https://github.com/wereallmonks/classsed-react-firebase-functions","stars":0,"forks":0,"issues":5,"language":"JavaScript","description":null,"topics":[],"score":2083,"global_rank":316556},{"name":"eeejay/vidyo-accessibility","owner":"eeejay","html_url":"https://github.com/eeejay/vidyo-accessibility","stars":0,"forks":0,"issues":0,"language":"JavaScript","description":"A WebExtension to make VidyoConnect just a bit accessible","topics":[],"score":2083,"global_rank":316557},{"name":"cuteshaun/Mock-server","owner":"cuteshaun","html_url":"https://github.com/cuteshaun/Mock-server","stars":0,"forks":0,"issues":0,"language":"JavaScript","description":"Mock server on Node.js (express)","topics":[],"score":2083,"global_rank":316562},{"name":"kayjayhogan/ecommerce-page","owner":"kayjayhogan","html_url":"https://github.com/kayjayhogan/ecommerce-page","stars":0,"forks":0,"issues":6,"language":"JavaScript","description":"A functional example of an e-commerce site","topics":[],"score":2083,"global_rank":316563},{"name":"ksleeq21/cloud-developer-minigram-serverless","owner":"ksleeq21","html_url":"https://github.com/ksleeq21/cloud-developer-minigram-serverless","stars":0,"forks":0,"issues":27,"language":"TypeScript","description":"Minigram Serverless","topics":[],"score":2083,"global_rank":316567},{"name":"ksleeq21/cloud-developer-serverless-todo","owner":"ksleeq21","html_url":"https://github.com/ksleeq21/cloud-developer-serverless-todo","stars":0,"forks":0,"issues":25,"language":"TypeScript","description":"Serverless todo","topics":[],"score":2083,"global_rank":316568},{"name":"kmojabe/W7D3","owner":"kmojabe","html_url":"https://github.com/kmojabe/W7D3","stars":0,"forks":0,"issues":0,"language":"JavaScript","description":null,"topics":[],"score":2083,"global_rank":316574},{"name":"gmackie/todo-points","owner":"gmackie","html_url":"https://github.com/gmackie/todo-points","stars":0,"forks":0,"issues":21,"language":"TypeScript","description":"the frontend for todo points / gameification as a service","topics":[],"score":2083,"global_rank":316580},{"name":"ALawley/epicodus-recipe-suggester","owner":"ALawley","html_url":"https://github.com/ALawley/epicodus-recipe-suggester","stars":0,"forks":2,"issues":0,"language":"JavaScript","description":"Capstone group project for the Epicodus Intro Class. Site that allows user to input ingredients and suggests recipes to them.","topics":[],"score":2083,"global_rank":316581},{"name":"aysendl/EatDaBurgerApp","owner":"aysendl","html_url":"https://github.com/aysendl/EatDaBurgerApp","stars":0,"forks":0,"issues":5,"language":"JavaScript","description":null,"topics":[],"score":2083,"global_rank":316583},{"name":"bikegcy/miniMek","owner":"bikegcy","html_url":"https://github.com/bikegcy/miniMek","stars":0,"forks":0,"issues":0,"language":"JavaScript","description":"Mini Mek project built with MERN and Redux","topics":[],"score":2083,"global_rank":316584},{"name":"balassit/SendBirdSample","owner":"balassit","html_url":"https://github.com/balassit/SendBirdSample","stars":0,"forks":0,"issues":0,"language":"JavaScript","description":null,"topics":[],"score":2083,"global_rank":316585},{"name":"coolkp/landing_page","owner":"coolkp","html_url":"https://github.com/coolkp/landing_page","stars":0,"forks":0,"issues":20,"language":"JavaScript","description":null,"topics":[],"score":2083,"global_rank":316587},{"name":"paulritzman/Lab18_MVC5_Movie","owner":"paulritzman","html_url":"https://github.com/paulritzman/Lab18_MVC5_Movie","stars":0,"forks":0,"issues":0,"language":"JavaScript","description":"Tutorial on ASP.NET MVC 5 from Microsoft: https://docs.microsoft.com/en-us/aspnet/mvc/overview/getting-started/introduction/getting-started","topics":[],"score":2083,"global_rank":316590},{"name":"madeby254/SQL-Library-Manager","owner":"madeby254","html_url":"https://github.com/madeby254/SQL-Library-Manager","stars":0,"forks":0,"issues":12,"language":"JavaScript","description":null,"topics":[],"score":2083,"global_rank":316592},{"name":"itsOrD/piperjdrake","owner":"itsOrD","html_url":"https://github.com/itsOrD/piperjdrake","stars":0,"forks":0,"issues":13,"language":"JavaScript","description":"A concept app primarily being used to practice react-native","topics":[],"score":2083,"global_rank":316593},{"name":"MaxTran96/basic-burger-builder-app","owner":"MaxTran96","html_url":"https://github.com/MaxTran96/basic-burger-builder-app","stars":0,"forks":0,"issues":0,"language":"JavaScript","description":"a work-in-progress burger builder app using React, Redux, and firebase","topics":[],"score":2083,"global_rank":316594},{"name":"yaya2020130/adulthomecarebackend","owner":"yaya2020130","html_url":"https://github.com/yaya2020130/adulthomecarebackend","stars":0,"forks":0,"issues":11,"language":"JavaScript","description":null,"topics":[],"score":2083,"global_rank":316595},{"name":"amaliaclaire/amalia-website-2018","owner":"amaliaclaire","html_url":"https://github.com/amaliaclaire/amalia-website-2018","stars":0,"forks":0,"issues":0,"language":"JavaScript","description":"personal website ","topics":[],"score":2083,"global_rank":316597},{"name":"AlexFox1777/React_Tests","owner":"AlexFox1777","html_url":"https://github.com/AlexFox1777/React_Tests","stars":0,"forks":0,"issues":26,"language":"TypeScript","description":null,"topics":[],"score":2083,"global_rank":316600}]